qfilter/__init__.py
qfilter/mixins.py
qfilter/utils.py
qfilter/vars.py
qfilter/forms/__init__.py
qfilter/forms/query.py
qfilter/static/jquery.formset.js
qfilter/static/qquery.css
qfilter/static/qquery.js
qfilter/templates/qfilter/qquery_filter.html
qfilter/templates/qfilter/qquery_filter_modal.html
django_q_filter-0.1.dist-info/LICENSE.md
django_q_filter-0.1.dist-info/METADATA
django_q_filter-0.1.dist-info/WHEEL
django_q_filter-0.1.dist-info/top_level.txt
django_q_filter-0.1.dist-info/RECORD
